my_lib/__init__.py
my_lib/hello.py
rolyson/__init__.py
rolyson/hello.py
rolyson/validate.py
rolyson-0.2.dist-info/METADATA
rolyson-0.2.dist-info/WHEEL
rolyson-0.2.dist-info/top_level.txt
rolyson-0.2.dist-info/RECORD
