Metadata-Version: 2.1
Name: rolyson
Version: 0.2
Summary: Biblioteca de funções comuns para meus projetos Django
Home-page: https://github.com/Rolyson/lib-rolyson
Author: Rolyson
Author-email: rolysonrocha@gmail.com
License: UNKNOWN
Platform: UNKNOWN
Classifier: Programming Language :: Python :: 3
Classifier: License :: OSI Approved :: MIT License
Classifier: Operating System :: OS Independent
Requires-Python: >=3.6
